centaur_technical_indicators/__init__.py
centaur_technical_indicators/centaur_technical_indicators.cpython-312-powerpc64le-linux-gnu.so
centaur_technical_indicators-1.0.1.dist-info/METADATA
centaur_technical_indicators-1.0.1.dist-info/WHEEL
centaur_technical_indicators-1.0.1.dist-info/licenses/LICENSE-MIT
centaur_technical_indicators-1.0.1.dist-info/RECORD
